{
  "clips": {
    "zaag": {
      "id": "zaag",
      "trackId": "ckh",
      "name": "mic 14 [2026-07-07 211313].aif",
      "startBeat": 0.0,
      "lengthBeats": 560.0,
      "offsetBeats": 0.0,
      "source": {
        "type": "Audio",
        "path": "samples/mic 14 [2026-07-07 211313].aif",
        "sampleRate": 48000.0,
        "channels": 1,
        "lengthSamples": 18432000,
        "timeStretchMode": "Signalsmith",
        "sourceBpmOrigin": "Inherited"
      },
      "araEnabled": false,
      "araBypassed": false,
      "laneIndex": 3,
      "gain": 0.18,
      "fadeInBeats": 0.0,
      "fadeOutBeats": 0.0,
      "fadeCurve": 1.0,
      "loopEnabled": false,
      "reversed": false,
      "swing": {
        "amount": 0.0,
        "mode": "eighth"
      }
    },
    "zaai": {
      "id": "zaai",
      "trackId": "ckh",
      "name": "mic 15 [2026-07-07 211317].aif",
      "startBeat": 0.0,
      "lengthBeats": 632.0,
      "offsetBeats": 0.0,
      "source": {
        "type": "Audio",
        "path": "samples/mic 15 [2026-07-07 211317].aif",
        "sampleRate": 48000.0,
        "channels": 1,
        "lengthSamples": 18432000,
        "timeStretchMode": "Signalsmith",
        "sourceBpmOrigin": "Inherited"
      },
      "araEnabled": false,
      "araBypassed": false,
      "laneIndex": 4,
      "gain": 0.1,
      "fadeInBeats": 0.0,
      "fadeOutBeats": 0.0,
      "fadeCurve": 1.0,
      "loopEnabled": false,
      "reversed": false,
      "swing": {
        "amount": 0.0,
        "mode": "eighth"
      }
    },
    "zaak": {
      "id": "zaak",
      "trackId": "ckh",
      "name": "mic 16 [2026-07-07 211323].aif",
      "startBeat": 0.0,
      "lengthBeats": 560.0,
      "offsetBeats": 0.0,
      "source": {
        "type": "Audio",
        "path": "samples/mic 16 [2026-07-07 211323].aif",
        "sampleRate": 48000.0,
        "channels": 1,
        "lengthSamples": 18432000,
        "timeStretchMode": "Signalsmith",
        "sourceBpmOrigin": "Inherited"
      },
      "araEnabled": false,
      "araBypassed": false,
      "laneIndex": 5,
      "gain": 0.23,
      "fadeInBeats": 0.0,
      "fadeOutBeats": 0.0,
      "fadeCurve": 1.0,
      "loopEnabled": false,
      "reversed": false,
      "swing": {
        "amount": 0.0,
        "mode": "eighth"
      }
    },
    "zaal": {
      "id": "zaal",
      "trackId": "ckh",
      "name": "mic 18 [2026-07-07 211328].aif",
      "startBeat": 0.0,
      "lengthBeats": 438.0,
      "offsetBeats": 0.0,
      "source": {
        "type": "Audio",
        "path": "samples/mic 18 [2026-07-07 211328].aif",
        "sampleRate": 48000.0,
        "channels": 1,
        "lengthSamples": 18432000,
        "timeStretchMode": "Signalsmith",
        "sourceBpmOrigin": "Inherited"
      },
      "araEnabled": false,
      "araBypassed": false,
      "laneIndex": 6,
      "gain": 0.12,
      "fadeInBeats": 0.0,
      "fadeOutBeats": 0.0,
      "fadeCurve": 1.0,
      "loopEnabled": false,
      "reversed": false,
      "swing": {
        "amount": 0.0,
        "mode": "eighth"
      }
    },
    "zaan": {
      "id": "zaan",
      "trackId": "ugb",
      "name": "BIJAN PONDEROSA Dimitri 2026  04 A Present.wav",
      "startBeat": 0.0,
      "lengthBeats": 756.7395833333334,
      "offsetBeats": 0.0,
      "source": {
        "type": "Audio",
        "path": "samples/BIJAN PONDEROSA Dimitri 2026  04 A Present.wav",
        "sampleRate": 44100.0,
        "channels": 2,
        "lengthSamples": 16686029,
        "timeStretchMode": "Signalsmith",
        "sourceBpmOrigin": "Inherited"
      },
      "araEnabled": false,
      "araBypassed": false,
      "gain": 1.0,
      "fadeInBeats": 0.0,
      "fadeOutBeats": 0.0,
      "fadeCurve": 1.0,
      "loopEnabled": false,
      "reversed": false,
      "swing": {
        "amount": 0.0,
        "mode": "eighth"
      }
    },
    "zaar": {
      "id": "zaar",
      "trackId": "act",
      "name": "mic 11 [2026-07-07 212743].aif",
      "startBeat": 0.0,
      "lengthBeats": 534.0,
      "offsetBeats": 0.0,
      "source": {
        "type": "Audio",
        "path": "samples/mic 11 [2026-07-07 212743].aif",
        "sampleRate": 48000.0,
        "channels": 1,
        "lengthSamples": 26880000,
        "timeStretchMode": "Signalsmith",
        "sourceBpmOrigin": "Inherited"
      },
      "araEnabled": false,
      "araBypassed": false,
      "laneIndex": 2,
      "gain": 0.16,
      "fadeInBeats": 0.0,
      "fadeOutBeats": 0.0,
      "fadeCurve": 1.0,
      "loopEnabled": false,
      "reversed": false,
      "swing": {
        "amount": 0.0,
        "mode": "eighth"
      }
    },
    "zaat": {
      "id": "zaat",
      "trackId": "act",
      "name": "mic 15 [2026-07-07 212800].aif",
      "startBeat": 0.0,
      "lengthBeats": 430.0,
      "offsetBeats": 0.0,
      "source": {
        "type": "Audio",
        "path": "samples/mic 15 [2026-07-07 212800].aif",
        "sampleRate": 48000.0,
        "channels": 1,
        "lengthSamples": 26880000,
        "timeStretchMode": "Signalsmith",
        "sourceBpmOrigin": "Inherited"
      },
      "araEnabled": false,
      "araBypassed": false,
      "laneIndex": 4,
      "gain": 0.09,
      "fadeInBeats": 0.0,
      "fadeOutBeats": 0.0,
      "fadeCurve": 1.0,
      "loopEnabled": false,
      "reversed": false,
      "swing": {
        "amount": 0.0,
        "mode": "eighth"
      }
    },
    "zaau": {
      "id": "zaau",
      "trackId": "act",
      "name": "mic 17 [2026-07-07 212808].aif",
      "startBeat": 0.0,
      "lengthBeats": 1120.0,
      "offsetBeats": 0.0,
      "source": {
        "type": "Audio",
        "path": "samples/mic 17 [2026-07-07 212808].aif",
        "sampleRate": 48000.0,
        "channels": 1,
        "lengthSamples": 26880000,
        "timeStretchMode": "Signalsmith",
        "sourceBpmOrigin": "Inherited"
      },
      "araEnabled": false,
      "araBypassed": false,
      "laneIndex": 5,
      "gain": 0.14,
      "fadeInBeats": 0.0,
      "fadeOutBeats": 0.0,
      "fadeCurve": 1.0,
      "loopEnabled": false,
      "reversed": false,
      "swing": {
        "amount": 0.0,
        "mode": "eighth"
      }
    },
    "zaav": {
      "id": "zaav",
      "trackId": "lev",
      "name": "BIJAN PONDEROSA Dimitri 2026 05 While The I Is Shining-06.wav",
      "startBeat": 0.0,
      "lengthBeats": 1107.3333333333333,
      "offsetBeats": 0.0,
      "source": {
        "type": "Audio",
        "path": "samples/BIJAN PONDEROSA Dimitri 2026 05 While The I Is Shining-06.wav",
        "sampleRate": 44100.0,
        "channels": 2,
        "lengthSamples": 24416746,
        "timeStretchMode": "Signalsmith",
        "sourceBpmOrigin": "Inherited"
      },
      "araEnabled": false,
      "araBypassed": false,
      "gain": 1.0,
      "fadeInBeats": 0.0,
      "fadeOutBeats": 0.0,
      "fadeCurve": 1.0,
      "loopEnabled": false,
      "reversed": false,
      "swing": {
        "amount": 0.0,
        "mode": "eighth"
      }
    },
    "pwha": {
      "id": "pwha",
      "trackId": "ckh",
      "name": "mic 14 [2026-07-07 211313].aif",
      "startBeat": 762.0,
      "lengthBeats": 6.0,
      "offsetBeats": 762.0,
      "source": {
        "type": "Audio",
        "path": "samples/mic 14 [2026-07-07 211313].aif",
        "sampleRate": 48000.0,
        "channels": 1,
        "lengthSamples": 18432000,
        "timeStretchMode": "Signalsmith",
        "sourceBpmOrigin": "Inherited"
      },
      "araEnabled": false,
      "araBypassed": false,
      "laneIndex": 3,
      "gain": 0.18,
      "fadeInBeats": 0.0,
      "fadeOutBeats": 0.0,
      "fadeCurve": 1.0,
      "loopEnabled": false,
      "reversed": false,
      "swing": {
        "amount": 0.0,
        "mode": "eighth"
      }
    },
    "zifd": {
      "id": "zifd",
      "trackId": "ckh",
      "name": "mic 14 [2026-07-07 211313].aif",
      "startBeat": 722.0,
      "lengthBeats": 40.0,
      "offsetBeats": 722.0,
      "source": {
        "type": "Audio",
        "path": "samples/mic 14 [2026-07-07 211313].aif",
        "sampleRate": 48000.0,
        "channels": 1,
        "lengthSamples": 18432000,
        "timeStretchMode": "Signalsmith",
        "sourceBpmOrigin": "Inherited"
      },
      "araEnabled": false,
      "araBypassed": false,
      "laneIndex": 3,
      "gain": 0.18,
      "fadeInBeats": 0.0,
      "fadeOutBeats": 0.0,
      "fadeCurve": 1.0,
      "loopEnabled": false,
      "reversed": false,
      "swing": {
        "amount": 0.0,
        "mode": "eighth"
      }
    },
    "mboe": {
      "id": "mboe",
      "trackId": "ckh",
      "name": "mic 14 [2026-07-07 211313].aif",
      "startBeat": 696.0,
      "lengthBeats": 26.0,
      "offsetBeats": 696.0,
      "source": {
        "type": "Audio",
        "path": "samples/mic 14 [2026-07-07 211313].aif",
        "sampleRate": 48000.0,
        "channels": 1,
        "lengthSamples": 18432000,
        "timeStretchMode": "Signalsmith",
        "sourceBpmOrigin": "Inherited"
      },
      "araEnabled": false,
      "araBypassed": false,
      "laneIndex": 3,
      "gain": 0.18,
      "fadeInBeats": 0.0,
      "fadeOutBeats": 0.0,
      "fadeCurve": 1.0,
      "loopEnabled": false,
      "reversed": false,
      "swing": {
        "amount": 0.0,
        "mode": "eighth"
      }
    },
    "pdwm": {
      "id": "pdwm",
      "trackId": "ckh",
      "name": "mic 14 [2026-07-07 211313].aif",
      "startBeat": 622.0,
      "lengthBeats": 74.0,
      "offsetBeats": 622.0,
      "source": {
        "type": "Audio",
        "path": "samples/mic 14 [2026-07-07 211313].aif",
        "sampleRate": 48000.0,
        "channels": 1,
        "lengthSamples": 18432000,
        "timeStretchMode": "Signalsmith",
        "sourceBpmOrigin": "Inherited"
      },
      "araEnabled": false,
      "araBypassed": false,
      "laneIndex": 3,
      "gain": 0.18,
      "fadeInBeats": 0.0,
      "fadeOutBeats": 0.0,
      "fadeCurve": 1.0,
      "loopEnabled": false,
      "reversed": false,
      "swing": {
        "amount": 0.0,
        "mode": "eighth"
      }
    },
    "eelh": {
      "id": "eelh",
      "trackId": "ckh",
      "name": "mic 14 [2026-07-07 211313].aif",
      "startBeat": 592.0,
      "lengthBeats": 30.0,
      "offsetBeats": 592.0,
      "source": {
        "type": "Audio",
        "path": "samples/mic 14 [2026-07-07 211313].aif",
        "sampleRate": 48000.0,
        "channels": 1,
        "lengthSamples": 18432000,
        "timeStretchMode": "Signalsmith",
        "sourceBpmOrigin": "Inherited"
      },
      "araEnabled": false,
      "araBypassed": false,
      "laneIndex": 3,
      "gain": 0.18,
      "fadeInBeats": 0.0,
      "fadeOutBeats": 0.0,
      "fadeCurve": 1.0,
      "loopEnabled": false,
      "reversed": false,
      "swing": {
        "amount": 0.0,
        "mode": "eighth"
      }
    },
    "dtst": {
      "id": "dtst",
      "trackId": "ckh",
      "name": "mic 14 [2026-07-07 211313].aif",
      "startBeat": 560.0,
      "lengthBeats": 32.0,
      "offsetBeats": 560.0,
      "source": {
        "type": "Audio",
        "path": "samples/mic 14 [2026-07-07 211313].aif",
        "sampleRate": 48000.0,
        "channels": 1,
        "lengthSamples": 18432000,
        "timeStretchMode": "Signalsmith",
        "sourceBpmOrigin": "Inherited"
      },
      "araEnabled": false,
      "araBypassed": false,
      "laneIndex": 3,
      "gain": 0.18,
      "fadeInBeats": 0.0,
      "fadeOutBeats": 0.0,
      "fadeCurve": 1.0,
      "loopEnabled": false,
      "reversed": false,
      "swing": {
        "amount": 0.0,
        "mode": "eighth"
      }
    },
    "zagc": {
      "id": "zagc",
      "trackId": "ckh",
      "name": "mic 15 [2026-07-07 211317].aif",
      "startBeat": 760.0,
      "lengthBeats": 8.0,
      "offsetBeats": 760.0,
      "source": {
        "type": "Audio",
        "path": "samples/mic 15 [2026-07-07 211317].aif",
        "sampleRate": 48000.0,
        "channels": 1,
        "lengthSamples": 18432000,
        "timeStretchMode": "Signalsmith",
        "sourceBpmOrigin": "Inherited"
      },
      "araEnabled": false,
      "araBypassed": false,
      "laneIndex": 4,
      "gain": 0.1,
      "fadeInBeats": 0.0,
      "fadeOutBeats": 0.0,
      "fadeCurve": 1.0,
      "loopEnabled": false,
      "reversed": false,
      "swing": {
        "amount": 0.0,
        "mode": "eighth"
      }
    },
    "oxph": {
      "id": "oxph",
      "trackId": "ckh",
      "name": "mic 15 [2026-07-07 211317].aif",
      "startBeat": 632.0,
      "lengthBeats": 128.0,
      "offsetBeats": 632.0,
      "source": {
        "type": "Audio",
        "path": "samples/mic 15 [2026-07-07 211317].aif",
        "sampleRate": 48000.0,
        "channels": 1,
        "lengthSamples": 18432000,
        "timeStretchMode": "Signalsmith",
        "sourceBpmOrigin": "Inherited"
      },
      "araEnabled": false,
      "araBypassed": false,
      "laneIndex": 4,
      "gain": 0.1,
      "fadeInBeats": 0.0,
      "fadeOutBeats": 0.0,
      "fadeCurve": 1.0,
      "loopEnabled": false,
      "reversed": false,
      "swing": {
        "amount": 0.0,
        "mode": "eighth"
      }
    },
    "uxdo": {
      "id": "uxdo",
      "trackId": "ckh",
      "name": "mic 16 [2026-07-07 211323].aif",
      "startBeat": 698.0,
      "lengthBeats": 70.0,
      "offsetBeats": 698.0,
      "source": {
        "type": "Audio",
        "path": "samples/mic 16 [2026-07-07 211323].aif",
        "sampleRate": 48000.0,
        "channels": 1,
        "lengthSamples": 18432000,
        "timeStretchMode": "Signalsmith",
        "sourceBpmOrigin": "Inherited"
      },
      "araEnabled": false,
      "araBypassed": false,
      "laneIndex": 5,
      "gain": 0.23,
      "fadeInBeats": 0.0,
      "fadeOutBeats": 0.0,
      "fadeCurve": 1.0,
      "loopEnabled": false,
      "reversed": false,
      "swing": {
        "amount": 0.0,
        "mode": "eighth"
      }
    },
    "jbvj": {
      "id": "jbvj",
      "trackId": "ckh",
      "name": "mic 16 [2026-07-07 211323].aif",
      "startBeat": 560.0,
      "lengthBeats": 138.0,
      "offsetBeats": 560.0,
      "source": {
        "type": "Audio",
        "path": "samples/mic 16 [2026-07-07 211323].aif",
        "sampleRate": 48000.0,
        "channels": 1,
        "lengthSamples": 18432000,
        "timeStretchMode": "Signalsmith",
        "sourceBpmOrigin": "Inherited"
      },
      "araEnabled": false,
      "araBypassed": false,
      "laneIndex": 5,
      "gain": 0.23,
      "fadeInBeats": 0.0,
      "fadeOutBeats": 0.0,
      "fadeCurve": 1.0,
      "loopEnabled": false,
      "reversed": false,
      "swing": {
        "amount": 0.0,
        "mode": "eighth"
      }
    },
    "zumb": {
      "id": "zumb",
      "trackId": "ckh",
      "name": "mic 18 [2026-07-07 211328].aif",
      "startBeat": 762.0,
      "lengthBeats": 6.0,
      "offsetBeats": 762.0,
      "source": {
        "type": "Audio",
        "path": "samples/mic 18 [2026-07-07 211328].aif",
        "sampleRate": 48000.0,
        "channels": 1,
        "lengthSamples": 18432000,
        "timeStretchMode": "Signalsmith",
        "sourceBpmOrigin": "Inherited"
      },
      "araEnabled": false,
      "araBypassed": false,
      "laneIndex": 6,
      "gain": 0.12,
      "fadeInBeats": 0.0,
      "fadeOutBeats": 0.0,
      "fadeCurve": 1.0,
      "loopEnabled": false,
      "reversed": false,
      "swing": {
        "amount": 0.0,
        "mode": "eighth"
      }
    },
    "kvnx": {
      "id": "kvnx",
      "trackId": "ckh",
      "name": "mic 18 [2026-07-07 211328].aif",
      "startBeat": 524.0,
      "lengthBeats": 238.0,
      "offsetBeats": 524.0,
      "source": {
        "type": "Audio",
        "path": "samples/mic 18 [2026-07-07 211328].aif",
        "sampleRate": 48000.0,
        "channels": 1,
        "lengthSamples": 18432000,
        "timeStretchMode": "Signalsmith",
        "sourceBpmOrigin": "Inherited"
      },
      "araEnabled": false,
      "araBypassed": false,
      "laneIndex": 6,
      "gain": 0.12,
      "fadeInBeats": 0.0,
      "fadeOutBeats": 0.0,
      "fadeCurve": 1.0,
      "loopEnabled": false,
      "reversed": false,
      "swing": {
        "amount": 0.0,
        "mode": "eighth"
      }
    },
    "kjfw": {
      "id": "kjfw",
      "trackId": "ckh",
      "name": "mic 18 [2026-07-07 211328].aif",
      "startBeat": 454.0,
      "lengthBeats": 70.0,
      "offsetBeats": 454.0,
      "source": {
        "type": "Audio",
        "path": "samples/mic 18 [2026-07-07 211328].aif",
        "sampleRate": 48000.0,
        "channels": 1,
        "lengthSamples": 18432000,
        "timeStretchMode": "Signalsmith",
        "sourceBpmOrigin": "Inherited"
      },
      "araEnabled": false,
      "araBypassed": false,
      "laneIndex": 6,
      "gain": 0.12,
      "fadeInBeats": 0.0,
      "fadeOutBeats": 0.0,
      "fadeCurve": 1.0,
      "loopEnabled": false,
      "reversed": false,
      "swing": {
        "amount": 0.0,
        "mode": "eighth"
      }
    },
    "rhuq": {
      "id": "rhuq",
      "trackId": "ckh",
      "name": "mic 18 [2026-07-07 211328].aif",
      "startBeat": 438.0,
      "lengthBeats": 16.0,
      "offsetBeats": 438.0,
      "source": {
        "type": "Audio",
        "path": "samples/mic 18 [2026-07-07 211328].aif",
        "sampleRate": 48000.0,
        "channels": 1,
        "lengthSamples": 18432000,
        "timeStretchMode": "Signalsmith",
        "sourceBpmOrigin": "Inherited"
      },
      "araEnabled": false,
      "araBypassed": false,
      "laneIndex": 6,
      "gain": 0.12,
      "fadeInBeats": 0.0,
      "fadeOutBeats": 0.0,
      "fadeCurve": 1.0,
      "loopEnabled": false,
      "reversed": false,
      "swing": {
        "amount": 0.0,
        "mode": "eighth"
      }
    },
    "vuta": {
      "id": "vuta",
      "trackId": "act",
      "name": "mic 11 [2026-07-07 212743].aif",
      "startBeat": 960.0,
      "lengthBeats": 160.0,
      "offsetBeats": 960.0,
      "source": {
        "type": "Audio",
        "path": "samples/mic 11 [2026-07-07 212743].aif",
        "sampleRate": 48000.0,
        "channels": 1,
        "lengthSamples": 26880000,
        "timeStretchMode": "Signalsmith",
        "sourceBpmOrigin": "Inherited"
      },
      "araEnabled": false,
      "araBypassed": false,
      "laneIndex": 2,
      "gain": 0.16,
      "fadeInBeats": 0.0,
      "fadeOutBeats": 0.0,
      "fadeCurve": 1.0,
      "loopEnabled": false,
      "reversed": false,
      "swing": {
        "amount": 0.0,
        "mode": "eighth"
      }
    },
    "qnye": {
      "id": "qnye",
      "trackId": "act",
      "name": "mic 11 [2026-07-07 212743].aif",
      "startBeat": 534.0,
      "lengthBeats": 426.0,
      "offsetBeats": 534.0,
      "source": {
        "type": "Audio",
        "path": "samples/mic 11 [2026-07-07 212743].aif",
        "sampleRate": 48000.0,
        "channels": 1,
        "lengthSamples": 26880000,
        "timeStretchMode": "Signalsmith",
        "sourceBpmOrigin": "Inherited"
      },
      "araEnabled": false,
      "araBypassed": false,
      "laneIndex": 2,
      "gain": 0.16,
      "fadeInBeats": 0.0,
      "fadeOutBeats": 0.0,
      "fadeCurve": 1.0,
      "loopEnabled": false,
      "reversed": false,
      "swing": {
        "amount": 0.0,
        "mode": "eighth"
      }
    },
    "nijh": {
      "id": "nijh",
      "trackId": "act",
      "name": "mic 15 [2026-07-07 212800].aif",
      "startBeat": 940.0,
      "lengthBeats": 180.0,
      "offsetBeats": 940.0,
      "source": {
        "type": "Audio",
        "path": "samples/mic 15 [2026-07-07 212800].aif",
        "sampleRate": 48000.0,
        "channels": 1,
        "lengthSamples": 26880000,
        "timeStretchMode": "Signalsmith",
        "sourceBpmOrigin": "Inherited"
      },
      "araEnabled": false,
      "araBypassed": false,
      "laneIndex": 4,
      "gain": 0.09,
      "fadeInBeats": 0.0,
      "fadeOutBeats": 0.0,
      "fadeCurve": 1.0,
      "loopEnabled": false,
      "reversed": false,
      "swing": {
        "amount": 0.0,
        "mode": "eighth"
      }
    },
    "vzuc": {
      "id": "vzuc",
      "trackId": "act",
      "name": "mic 15 [2026-07-07 212800].aif",
      "startBeat": 568.0,
      "lengthBeats": 372.0,
      "offsetBeats": 568.0,
      "source": {
        "type": "Audio",
        "path": "samples/mic 15 [2026-07-07 212800].aif",
        "sampleRate": 48000.0,
        "channels": 1,
        "lengthSamples": 26880000,
        "timeStretchMode": "Signalsmith",
        "sourceBpmOrigin": "Inherited"
      },
      "araEnabled": false,
      "araBypassed": false,
      "laneIndex": 4,
      "gain": 0.09,
      "fadeInBeats": 0.0,
      "fadeOutBeats": 0.0,
      "fadeCurve": 1.0,
      "loopEnabled": false,
      "reversed": false,
      "swing": {
        "amount": 0.0,
        "mode": "eighth"
      }
    },
    "gibb": {
      "id": "gibb",
      "trackId": "act",
      "name": "mic 15 [2026-07-07 212800].aif",
      "startBeat": 550.0,
      "lengthBeats": 18.0,
      "offsetBeats": 550.0,
      "source": {
        "type": "Audio",
        "path": "samples/mic 15 [2026-07-07 212800].aif",
        "sampleRate": 48000.0,
        "channels": 1,
        "lengthSamples": 26880000,
        "timeStretchMode": "Signalsmith",
        "sourceBpmOrigin": "Inherited"
      },
      "araEnabled": false,
      "araBypassed": false,
      "laneIndex": 4,
      "gain": 0.09,
      "fadeInBeats": 0.0,
      "fadeOutBeats": 0.0,
      "fadeCurve": 1.0,
      "loopEnabled": false,
      "reversed": false,
      "swing": {
        "amount": 0.0,
        "mode": "eighth"
      }
    },
    "qont": {
      "id": "qont",
      "trackId": "act",
      "name": "mic 15 [2026-07-07 212800].aif",
      "startBeat": 430.0,
      "lengthBeats": 120.0,
      "offsetBeats": 430.0,
      "source": {
        "type": "Audio",
        "path": "samples/mic 15 [2026-07-07 212800].aif",
        "sampleRate": 48000.0,
        "channels": 1,
        "lengthSamples": 26880000,
        "timeStretchMode": "Signalsmith",
        "sourceBpmOrigin": "Inherited"
      },
      "araEnabled": false,
      "araBypassed": false,
      "laneIndex": 4,
      "gain": 0.09,
      "fadeInBeats": 0.0,
      "fadeOutBeats": 0.0,
      "fadeCurve": 1.0,
      "loopEnabled": false,
      "reversed": false,
      "swing": {
        "amount": 0.0,
        "mode": "eighth"
      }
    }
  },
  "clipPlugins": {}
}